mscan/__init__.py
mscan/main.py
mscan/scanner/__init__.py
mscan/scanner/arp.py
mscan/scanner/interface.py
mscan/scanner/multi_ping.py
mscan/scanner/network.py
mscan/scanner/ping.py
mscan/scanner/platform_detector.py
mscan/scanner/scanner.py
mscan/settings.py
mscan/static/assets/index-560f337d.css
mscan/static/assets/index-8def36ff.js
mscan/static/index.html
mscan/static/logo.png
modern_scan-0.2.1.dist-info/entry_points.txt
modern_scan-0.2.1.dist-info/METADATA
modern_scan-0.2.1.dist-info/WHEEL
modern_scan-0.2.1.dist-info/RECORD
