Metadata-Version: 2.1
Name: modern-scan
Version: 0.2.1
Summary: Modern network scanner
Author: thewh1teagle
Author-email: 61390950+thewh1teagle@users.noreply.github.com
Requires-Python: >=3.8,<4.0
Classifier: Programming Language :: Python :: 3
Classifier: Programming Language :: Python :: 3.8
Classifier: Programming Language :: Python :: 3.9
Classifier: Programming Language :: Python :: 3.10
Classifier: Programming Language :: Python :: 3.11
Requires-Dist: fastapi (>=0.89.1,<0.90.0)
Requires-Dist: icmplib (>=3.0.3,<4.0.0)
Requires-Dist: mac-vendor-lookup (>=0.1.12,<0.2.0)
Requires-Dist: psutil (>=5.9.4,<6.0.0)
Requires-Dist: uvicorn[standard] (>=0.20.0,<0.21.0)
